bib2tex/__init__.py
bib2tex/__main__.py
bib2tex/bibtex_filter.py
bib2tex/bibtex_parser.py
bib2tex/config.py
bib2tex/converter.py
bib2tex/custom_types.py
bib2tex/file_handler.py
bib2tex/format_schemes/default.json
bib2tex/format_schemes.py
bib2tex-0.3.5.dist-info/LICENSE
bib2tex-0.3.5.dist-info/METADATA
bib2tex-0.3.5.dist-info/WHEEL
bib2tex-0.3.5.dist-info/entry_points.txt
bib2tex-0.3.5.dist-info/RECORD
