Metadata-Version: 2.1
Name: bib2tex
Version: 0.3.5
Summary: Create a subset of BibTeX entries based on an author's name and covert it into a LaTeX list.
Home-page: https://codeberg.org/Cs137/bib2tex
License: MIT
Keywords: BibTeX,LaTeX
Author: Christian Schreinemachers (Cs137)
Requires-Python: >=3.11,<4.0
Classifier: License :: OSI Approved :: MIT License
Classifier: Programming Language :: Python :: 3
Classifier: Programming Language :: Python :: 3.11
Classifier: Programming Language :: Python :: 3.12
Requires-Dist: click (>=8.1.7,<9.0.0)
Project-URL: Repository, https://codeberg.org/Cs137/bib2tex
